kaliapay_modpy/__init__.py
kaliapay_modpy/kaliapay.py
kaliapay_modpy_beta_0.0.2-0.0.2.dist-info/METADATA
kaliapay_modpy_beta_0.0.2-0.0.2.dist-info/WHEEL
kaliapay_modpy_beta_0.0.2-0.0.2.dist-info/top_level.txt
kaliapay_modpy_beta_0.0.2-0.0.2.dist-info/RECORD
