Metadata-Version: 2.1
Name: kaliapay-modpy-beta-0.0.2
Version: 0.0.2
Summary: Module de paiement Kaliapay
Author: Fabio
Author-email: <nadefabrice83@gmail.com>
Keywords: python,paiement,kaliapay,module
Requires-Dist: requests
